fopl/__init__.py
fopl/__main__.py
fopl-0.0.3.dist-info/LICENSE
fopl-0.0.3.dist-info/METADATA
fopl-0.0.3.dist-info/WHEEL
fopl-0.0.3.dist-info/top_level.txt
fopl-0.0.3.dist-info/RECORD
